{
    "relationships": [
        {
            "relationshipId": 1,
            "relationshipName": "user",
            "otherEntityName": "user",
            "relationshipType": "many-to-one",
            "otherEntityField": "id"
        }
    ],
    "fields": [
        {
            "fieldId": 1,
            "fieldName": "title",
            "fieldType": "String",
            "fieldValidateRules": [
                "required"
            ]
        },
        {
            "fieldId": 2,
            "fieldName": "location",
            "fieldType": "String",
            "fieldValidateRules": [
                "required"
            ]
        },
        {
            "fieldId": 3,
            "fieldName": "description",
            "fieldType": "String",
            "fieldValidateRules": []
        }
    ],
    "changelogDate": "20151203191715",
    "dto": "no",
    "pagination": "no"
}